my_math_package/__init__.py
my_math_package/calculator.py
my_math_package/geometry.py
my_math_package/internal_utils.py
my_math_package_july56-1.0.1.dist-info/licenses/LICENSE
my_math_package_july56-1.0.1.dist-info/METADATA
my_math_package_july56-1.0.1.dist-info/WHEEL
my_math_package_july56-1.0.1.dist-info/top_level.txt
my_math_package_july56-1.0.1.dist-info/RECORD
