Metadata-Version: 2.4
Name: my-math-package-july56
Version: 1.0.1
Summary: A simple math library for demonstration
Author: Your Name
Author-email: Your Name <your.email@example.com>
License: MIT
Project-URL: Homepage, https://github.com/yourusername/my-math-package
Project-URL: Bug Reports, https://github.com/yourusername/my-math-package/issues
Keywords: math,calculator,geometry
Classifier: Development Status :: 4 - Beta
Classifier: Intended Audience :: Education
Classifier: License :: OSI Approved :: MIT License
Classifier: Programming Language :: Python :: 3
Classifier: Programming Language :: Python :: 3.8
Classifier: Programming Language :: Python :: 3.9
Classifier: Programming Language :: Python :: 3.10
Classifier: Programming Language :: Python :: 3.11
Requires-Python: >=3.8
License-File: LICENSE
Dynamic: author
Dynamic: license-file
Dynamic: requires-python
